LICENSE
README.md
isetool/__init__.py
isetool/cli.py
isetool/ise.py
isetool-1.0.3.dist-info/LICENSE
isetool-1.0.3.dist-info/METADATA
isetool-1.0.3.dist-info/WHEEL
isetool-1.0.3.dist-info/entry_points.txt
isetool-1.0.3.dist-info/RECORD
